mistrorpc/__init__.py
mistrorpc/connect.py
mistrorpc/decorator.py
mistrorpc/pickle.py
mistrorpc-0.1.0.dist-info/LICENSE
mistrorpc-0.1.0.dist-info/METADATA
mistrorpc-0.1.0.dist-info/WHEEL
mistrorpc-0.1.0.dist-info/top_level.txt
mistrorpc-0.1.0.dist-info/RECORD
