Metadata-Version: 2.1
Name: mistrorpc
Version: 0.1.0
Summary: Mistro RPC Protocol Library
Author: Li lingyi
Author-email: alan_sudo@yeah.net
Maintainer: Project VsingerXiaoice Group
Maintainer-email: alan_sudo@yeah.net
License: Project VsingerXiaoice License
Requires: fastapi
Requires: aiohttp
Requires: requests
Requires: pydantic
License-File: LICENSE
